setup.py
probability_dists/BinomialDistribution.py
probability_dists/GaussianDistribution.py
probability_dists/GeneralDistribution.py
probability_dists/__init__.py
probability_dists.egg-info/PKG-INFO
probability_dists.egg-info/SOURCES.txt
probability_dists.egg-info/dependency_links.txt
probability_dists.egg-info/not-zip-safe
probability_dists.egg-info/top_level.txt