Metadata-Version: 1.0
Name: probability-dists
Version: 1.1
Summary: Probability distributions: Gaussian & Binomial
Home-page: UNKNOWN
Author: UNKNOWN
Author-email: UNKNOWN
License: UNKNOWN
Platform: UNKNOWN
